tldfinder.py
tldfinder-1.0.2.dist-info/METADATA
tldfinder-1.0.2.dist-info/WHEEL
tldfinder-1.0.2.dist-info/entry_points.txt
tldfinder-1.0.2.dist-info/top_level.txt
tldfinder-1.0.2.dist-info/RECORD
