Metadata-Version: 2.1
Name: tldfinder
Version: 1.0.2
Summary: Discover bug bounty scopes associated with star top-level domains (TLDs).
Home-page: UNKNOWN
Author: Amirmohammad Safari
Author-email: amirmohammad@myyahoo.com
License: UNKNOWN
Platform: UNKNOWN
Classifier: Development Status :: 5 - Production/Stable
Classifier: Intended Audience :: Developers
Classifier: License :: OSI Approved :: MIT License
Classifier: Programming Language :: Python
Classifier: Programming Language :: Python :: 3
Classifier: Programming Language :: Python :: 3.6
Classifier: Programming Language :: Python :: 3.7
Classifier: Programming Language :: Python :: 3.8
Classifier: Programming Language :: Python :: 3.9
Requires-Dist: requests
Requires-Dist: argparse
